gyver/tests/__init__.py
gyver/tests/http/__init__.py
gyver/tests/http/exc.py
gyver/tests/http/helpers.py
gyver/tests/http/mocker.py
gyver/tests/http/mocker.pyi
gyver/tests/http/plugin.py
gyver/tests/http/typedef.py
gyver/tests/http/writer.py
gyver_tests-2.0.2.dist-info/METADATA
gyver_tests-2.0.2.dist-info/WHEEL
gyver_tests-2.0.2.dist-info/RECORD
