Metadata-Version: 2.1
Name: gyver-tests
Version: 2.0.2
Summary: 
Author: Gustavo Correa
Author-email: self.gustavocorrea@gmail.com
Requires-Python: >=3.9,<4.0
Classifier: Programming Language :: Python :: 3
Classifier: Programming Language :: Python :: 3.9
Classifier: Programming Language :: Python :: 3.10
Classifier: Programming Language :: Python :: 3.11
Classifier: Programming Language :: Python :: 3.12
Requires-Dist: faker (>=19.10.0,<20.0.0)
Requires-Dist: gyver (>=4.0.0,<5.0.0)
Requires-Dist: pytest (>=7.4.2,<8.0.0)
